financial_pie/__init__.py
financial_pie-0.1.0.dist-info/LICENSE
financial_pie-0.1.0.dist-info/METADATA
financial_pie-0.1.0.dist-info/WHEEL
financial_pie-0.1.0.dist-info/top_level.txt
financial_pie-0.1.0.dist-info/RECORD
